magik/__init__.py
magik/classifier.py
magik/cli.py
magik/config.py
magik/constants.py
magik/decorators.py
magik/deploy.py
magik/evaluators.py
magik/generate.py
magik/initialize.py
magik/internal_logger.py
magik/langchain_handler.py
magik/logger.py
magik/matchers.py
magik/metrics.py
magik/openai_helper.py
magik/run.py
magik/run_logger.py
magik/similarity.py
magik/sys_exec.py
magik/test_loader.py
magik/utils.py
magik/examples/__init__.py
magik/examples/assertions.py
magik/types/__init__.py
magik/types/test_run.py
magik-0.2.11.dist-info/METADATA
magik-0.2.11.dist-info/WHEEL
magik-0.2.11.dist-info/entry_points.txt
magik-0.2.11.dist-info/top_level.txt
magik-0.2.11.dist-info/RECORD
