Metadata-Version: 2.1
Name: magik
Version: 0.2.11
Summary: SDK to write and run tests for your LLM app
Home-page: UNKNOWN
Author: Magik Labs Team
Author-email: hello@magiklabs.app
License: UNKNOWN
Platform: UNKNOWN
Classifier: Programming Language :: Python :: 3
Classifier: License :: OSI Approved :: MIT License
Classifier: Operating System :: OS Independent
Requires-Python: >=3.6
Requires-Dist: aiohttp ==3.8.5
Requires-Dist: aiosignal ==1.3.1
Requires-Dist: annotated-types ==0.5.0
Requires-Dist: async-timeout ==4.0.2
Requires-Dist: attrs ==23.1.0
Requires-Dist: certifi ==2023.5.7
Requires-Dist: charset-normalizer ==3.2.0
Requires-Dist: colorlog ==6.7.0
Requires-Dist: dataclasses-json ==0.5.14
Requires-Dist: frozenlist ==1.3.3
Requires-Dist: greenlet ==2.0.2
Requires-Dist: idna ==3.4
Requires-Dist: langchain ==0.0.288
Requires-Dist: langsmith ==0.0.37
Requires-Dist: marshmallow ==3.20.1
Requires-Dist: multidict ==6.0.4
Requires-Dist: mypy ==1.4.1
Requires-Dist: mypy-extensions ==1.0.0
Requires-Dist: numexpr ==2.8.6
Requires-Dist: numpy ==1.23.5
Requires-Dist: openai ==0.27.8
Requires-Dist: packaging ==23.1
Requires-Dist: pydantic ==2.3.0
Requires-Dist: pydantic-core ==2.6.3
Requires-Dist: PyYAML ==6.0.1
Requires-Dist: requests ==2.31.0
Requires-Dist: tenacity ==8.2.2
Requires-Dist: tomli ==2.0.1
Requires-Dist: tqdm ==4.65.0
Requires-Dist: types-requests ==2.31.0.2
Requires-Dist: types-urllib3 ==1.26.25.14
Requires-Dist: typing-inspect ==0.9.0
Requires-Dist: typing-extensions ==4.7.1
Requires-Dist: urllib3 ==1.26.16
Requires-Dist: yarl ==1.9.2
